django_ktdatatable_view/__init__.py
django_ktdatatable_view/base_ktdatatable_view.py
django_ktdatatable_view/mixins.py
django_ktdatatable_view-1.6.3.dist-info/LICENSE
django_ktdatatable_view-1.6.3.dist-info/METADATA
django_ktdatatable_view-1.6.3.dist-info/WHEEL
django_ktdatatable_view-1.6.3.dist-info/top_level.txt
django_ktdatatable_view-1.6.3.dist-info/RECORD
