Metadata-Version: 2.1
Name: django-ktdatatable-view
Version: 1.6.3
Summary: Django KTDatatable View
Home-page: https://gitlab.com/longbowou/django-ktdatatable-view
Author: Longbowou
Author-email: blandedaniel@gmail.com
Project-URL: Bug Tracker, https://gitlab.com/longbowou/django-ktdatatable-view/-/issues
Classifier: Programming Language :: Python :: 3
Classifier: License :: OSI Approved :: MIT License
Classifier: Operating System :: OS Independent
Requires-Python: >=3.6
License-File: LICENSE
